aries.py
aries_controller-0.7.0.dist-info/entry_points.txt
aries_controller-0.7.0.dist-info/LICENSE
aries_controller-0.7.0.dist-info/WHEEL
aries_controller-0.7.0.dist-info/METADATA
aries_controller-0.7.0.dist-info/RECORD
