Metadata-Version: 2.1
Name: aries-controller
Version: 0.7.0
Summary: An unofficial telnet wrapper for "ARIES / LYNX" motor controller by Kohzu Precision Co.,Ltd.
Home-page: https://github.com/2-propanol/aries_controller
License: Zlib
Author: 2-propanol
Author-email: nuclear.fusion.247@gmail.com
Requires-Python: >=3.6,<4.0
Classifier: License :: OSI Approved
Classifier: Programming Language :: Python :: 3
Classifier: Programming Language :: Python :: 3.6
Classifier: Programming Language :: Python :: 3.7
Classifier: Programming Language :: Python :: 3.8
Classifier: Programming Language :: Python :: 3.9
